ocriiif/__init__.py
ocriiif-0.0.3.dist-info/LICENSE
ocriiif-0.0.3.dist-info/METADATA
ocriiif-0.0.3.dist-info/WHEEL
ocriiif-0.0.3.dist-info/top_level.txt
ocriiif-0.0.3.dist-info/RECORD
