Metadata-Version: 2.1
Name: ocriiif
Version: 0.0.3
Summary: Library for converting IIIF resources to OCR data
Home-page: https://github.com/digirati-co-uk/ocriiif
Author: Matt McGrattan
Author-email: matt.mcgrattan@digirati.com
License: UNKNOWN
Platform: UNKNOWN
Classifier: Programming Language :: Python :: 3
Classifier: License :: OSI Approved :: MIT License
Classifier: Operating System :: OS Independent
Requires-Python: >=3.7
Requires-Dist: Pillow (>=8.0.1)
Requires-Dist: pytesseract (>=0.3.6)
Requires-Dist: certifi (>=2017.4.17)
Requires-Dist: chardet (<4,>=3.0.2)
Requires-Dist: idna (<3,>=2.5)
Requires-Dist: urllib3 (<1.27,>=1.21.1)
Requires-Dist: requests (>=2.25.0)
Requires-Dist: numpy (>=1.19.4)
